[{"user_id": "555", "requests": [{"time": "05.10.2019", "tape": "http://lenta.ru/l/r/EX/import.rss", "key_words": "\u0442\u0440\u0430\u043c\u043f, \u043c\u0435\u0440\u043a\u0435\u043b\u044c"}, {"time": "05.10.2019", "tape": "http://lenta.ru/l/r/EX/import.rss", "key_words": "\u0442\u0440\u0430\u043c\u043f, \u043c\u0435\u0440\u043a\u0435\u043b\u044c"}]}, {"user_id": "111", "requests": [{"time": "1.1.2001", "tape": "http://lenta.ru/l/r/EX/import.rss", "key_words": "\u0443\u0440\u0430 \u0443\u0440\u0430 \u0443\u0440\u0430"}]}, {"user_id": 444591160, "requests": [{"time": "Sat Oct  5 19:26:37 2019", "tape": "http://lenta.ru/l/r/EX/import.rss", "key_words": "\u0442\u0440\u0430\u043c\u043f"}]}]